LICENSE
MANIFEST.in
README.rst
requirements.txt
setup.py
odbrasil/__init__.py
odbrasil.egg-info/PKG-INFO
odbrasil.egg-info/SOURCES.txt
odbrasil.egg-info/dependency_links.txt
odbrasil.egg-info/not-zip-safe
odbrasil.egg-info/requires.txt
odbrasil.egg-info/top_level.txt
odbrasil/legislativo/__init__.py
odbrasil/legislativo/camara.py