Metadata-Version: 1.1
Name: odbrasil
Version: 0.1
Summary: A Python package for retrieving and parsing Brazilian government open data.
Home-page: https://github.com/perone/odbrasil/
Author: Christian S. Perone
Author-email: christian.perone@gmail.com
License: Apache License 2.0
Keywords: open data,parser,odbrasil,brasil
Platform: Any
Classifier: Development Status :: 4 - Beta
Classifier: License :: OSI Approved :: Apache Software License
Classifier: Operating System :: OS Independent
Classifier: Programming Language :: Python
Classifier: Topic :: Software Development :: Libraries :: Python Modules
